cxool/README.html
cxool/README.md
cxool/__init__.py
cxool/_version.py
cxool/cds_handler.py
cxool/cxool_cli.py
cxool/interpolation.py
cxool/plotting.py
cxool/specifications.py
cxool/examples/GermanNorthernSea/example_German_Northern_sea.py
cxool/examples/GermanNorthernSea/nordseedeu10km_grid.nc
cxool/examples/MexicanCaribbean/caribemex10km_grid.nc
cxool/examples/MexicanCaribbean/example_Mexican_caribbean.py
cxool/examples/ROMS_example/README.html
cxool/examples/ROMS_example/README.md
cxool/examples/ROMS_example/cxool_instructions.txt
cxool/examples/ROMS_example/External/inluum.in
cxool/examples/ROMS_example/Include/gulfofmexico.h
cxool/examples/ROMS_example/data/inluum_grid.nc
cxool/examples/ROMS_example/data/run_cxool_example.py
cxool/tests/conftest.py
cxool/tests/nordseedeu10km_grid.nc
cxool/tests/reference_Deu_NS.nc
cxool/tests/test_cds_handler.py
cxool/tests/test_cli_parser.py
cxool/tests/test_interpolation.py
cxool/tests/test_northern_sea.py
cxool/tests/test_plotting.py
cxool-1.0.2.dist-info/METADATA
cxool-1.0.2.dist-info/WHEEL
cxool-1.0.2.dist-info/entry_points.txt
cxool-1.0.2.dist-info/licenses/LICENSE
cxool-1.0.2.dist-info/RECORD
