Metadata-Version: 2.4
Name: CXool
Version: 1.0.2
Summary: A command-line toolbox for preparing ERA5 atmospheric data for ocean modelling with ROMS.
Project-URL: Documentation, https://pypi.org/project/CXool/
Project-URL: Source, https://github.com/C-Xool/C-Xool
Project-URL: Tracker, https://github.com/C-Xool/C-Xool/issues
Author-email: Carlos Argáez García <cargaezg@iingen.unam.mx>, Simon Klüpfel <simon.kluepfel@gmail.com>, María Eugenia Allende Arandia <mallendea@iingen.unam.mx>, Christian Mario Appendini Albrechtsen <cappendinia@iingen.unam.mx>
License-Expression: GPL-3.0
License-File: LICENSE
Requires-Python: >=3.8
Requires-Dist: cartopy>=0.23.0
Requires-Dist: cdsapi>=0.7.3
Requires-Dist: cmocean>=4.0.3
Requires-Dist: dask>=2024.6.0
Requires-Dist: matplotlib>=3.8.4
Requires-Dist: netcdf4>=1.6.5
Requires-Dist: numpy>=1.26.4
Requires-Dist: scipy>=1.13.1
Requires-Dist: xarray>=2024.6.0
